LICENSE
MANIFEST.in
README.md
setup.py
gin/__init__.py
gin/__main__.py
gin/gin.py
gin/parser.py
gin_cli.egg-info/PKG-INFO
gin_cli.egg-info/SOURCES.txt
gin_cli.egg-info/dependency_links.txt
gin_cli.egg-info/entry_points.txt
gin_cli.egg-info/top_level.txt