Metadata-Version: 1.0
Name: gin-cli
Version: 0.0.4
Summary: GIN Python command line application bare bones template.
Home-page: https://github.com/Javanile/GIN
Author: Francesco Bianco
Author-email: bianco@javanile.org
License: UNKNOWN
Platform: UNKNOWN
